Metadata-Version: 2.1
Name: mathematical-distributions-v001
Version: 0.1
Summary: Gaussian and Binomial distributions
Home-page: UNKNOWN
Author: Evren Arslan
Author-email: earslan3e@gmail.com
License: UNKNOWN
Platform: UNKNOWN
